Metadata-Version: 2.1
Name: odoo8-addon-account-invoice-pricelist-sale-stock
Version: 8.0.2.0.0
Summary: Set pricelist from SO in invoice created from picking.
Home-page: http://therp.nl
Author: Therp BV,Odoo Community Association (OCA)
Author-email: support@odoo-community.org
License: AGPL-3
Platform: UNKNOWN
Classifier: Programming Language :: Python
Classifier: Framework :: Odoo
Classifier: License :: OSI Approved :: GNU Affero General Public License v3
Requires-Python: ~=2.7
Requires-Dist: odoo8-addon-account-invoice-pricelist-stock-account
Requires-Dist: odoo (<9.0a,>=8.0a)
